{
"People" : [
    {
        "first-name": "Aditya",
        "last-name": "Trehan",
        "phone": "+919930330521",
        "location": "Mumbai",
        "division-id": "OPS",
        "division-name": "Operations",
        "position-name": "Head of Operations",
        "email": "aditya.trehan@maersktankers.com",
        "ice-id": "",
        "segments": ""
    },
    {
        "first-name": "Ashfaq",
        "last-name": "Abdali",
        "phone": "+4529428834",
        "location": "Copenhagen",
        "division-id": "INTOPSCPH",
        "division-name": "Operations",
        "position-name": "Operator",
        "email": "Ashfaq.Abdali@maersktankers.com",
        "ice-id": "",
        "segments": "Intermediate"
    },
    {
        "first-name": "Ditte",
        "last-name": "Stensig",
        "phone": "+4528989852",
        "location": "Copenhagen",
        "division-id": "PARSERV",
        "division-name": "Partner Services",
        "position-name": "Partner Manager",
        "email": "ditte.stensig@maersktankers.com",
        "ice-id": "",
        "segments": ""
    },
    {
        "first-name": "Hans Ulrik",
        "last-name": "Norgaard",
        "phone": "+4521166025",
        "location": "Copenhagen",
        "division-id": "HTC",
        "division-name": "Chartering",
        "position-name": "Head of Chartering, Intermediate & Handytankers",
        "email": "hans.ulrik.norgaard@maersktankers.com",
        "ice-id": "",
        "segments": "Handy"
    },
    {
        "first-name": "Ulrich",
        "last-name": "Schittek",
        "phone": "+4531151929",
        "location": "Copenhagen",
        "division-id": "PARREL",
        "division-name": "Partner Relations",
        "position-name": "Head of Partner Relations",
        "email": "Ulrich.Schittek@maersktankers.com",
        "ice-id": "",
        "segments": ""
    },
    {
        "first-name": "Kim Wah Stephen",
        "last-name": "Chua",
        "phone": "+6596624522",
        "location": "Singapore",
        "division-id": "CHTSIN",
        "division-name": "Chartering",
        "position-name": "Charterer, Handytankers",
        "email": "Stephen.Chua@maersktankers.com",
        "ice-id": "",
        "segments": "Handy"
    },
    {
        "first-name": "Martin",
        "last-name": "Hansson",
        "phone": "+46736242472",
        "location": "Copenhagen",
        "division-id": "INTOPSCPH",
        "division-name": "Operations",
        "position-name": "Operator",
        "email": "Martin.Hansson@maersktankers.com",
        "ice-id": "",
        "segments": "Intermediate"
    },
    {
        "first-name": "Soren",
        "last-name": "Hempel",
        "phone": "+4530381146",
        "location": "Copenhagen",
        "division-id": "HTC",
        "division-name": "Chartering",
        "position-name": "Charterer",
        "email": "soren.hempel@maersktankers.com",
        "ice-id": "",
        "segments": "Handy"
    },
    {
        "first-name": "Benjamin",
        "last-name": "Davies",
        "phone": "+6590933074",
        "location": "Singapore",
        "division-id": "CHTSIN",
        "division-name": "Chartering",
        "position-name": "Charterer, Handytankers",
        "email": "Benjamin.Davies@maersktankers.com",
        "ice-id": "",
        "segments": "Handy"
    },
    {
        "first-name": "Allan",
        "last-name": "Jensen",
        "phone": "+4529325278",
        "location": "Copenhagen",
        "division-id": "INTOPSCPH",
        "division-name": "Operations",
        "position-name": "Vessel Operator",
        "email": "allan.jensen@maersktankers.com",
        "ice-id": "",
        "segments": "Intermediate"
    },
    {
        "first-name": "Jolyn",
        "last-name": "Tay",
        "phone": "+6590708292",
        "location": "Singapore",
        "division-id": "PARSERV",
        "division-name": "Partner Services",
        "position-name": "Partner Manager",
        "email": "jolyn.tay@maersktankers.com",
        "ice-id": "",
        "segments": ""
    },
    {
        "first-name": "Andreea Catalina",
        "last-name": "Alexe",
        "phone": "+4531193270",
        "location": "Copenhagen",
        "division-id": "INTOPSCPH",
        "division-name": "Operations",
        "position-name": "Operator",
        "email": "andreea.alexe@maersktankers.com",
        "ice-id": "",
        "segments": "Intermediate"
    },
    {
        "first-name": "Yao",
        "last-name": "Liu",
        "phone": "+651234567",
        "location": "Singapore",
        "division-id": "CHTSIN",
        "division-name": "Chartering",
        "position-name": "Charterer",
        "email": "yao.liu@maersktankers.com",
        "ice-id": "",
        "segments": "Handy"
    },
    {
        "first-name": "James",
        "last-name": "Killingsworth",
        "phone": "+6584828689",
        "location": "Singapore",
        "division-id": "PARSERV",
        "division-name": "Partner Services",
        "position-name": "Senior Business Manager",
        "email": "james.killingsworth@maersktankers.com",
        "ice-id": "",
        "segments": ""
    },
    {
        "first-name": "Johan",
        "last-name": "Esbensen",
        "phone": "+4540112450",
        "location": "Copenhagen",
        "division-id": "INTOPSCPH",
        "division-name": "Operations",
        "position-name": "Operations Manager, Intermediate",
        "email": "JohanWeihe.Esbensen@maersktankers.com",
        "ice-id": "",
        "segments": "Intermediate"
    },
    {
        "first-name": "Par",
        "last-name": "Bokman",
        "phone": "+4523453894",
        "location": "Copenhagen",
        "division-id": "BROCHART",
        "division-name": "Chartering",
        "position-name": "Charterer, Intermediate",
        "email": "Par.Bokman@maersktankers.com",
        "ice-id": "",
        "segments": "Intermediate"
    },
    {
        "first-name": "Lars",
        "last-name": "Bentzen",
        "phone": "+4540201434",
        "location": "Copenhagen",
        "division-id": "PARSERV",
        "division-name": "Partner Services",
        "position-name": "Head of Partner Services",
        "email": "lars.bentzen@maersktankers.com",
        "ice-id": "",
        "segments": ""
    },
    {
        "first-name": "Piyush",
        "last-name": "Jain",
        "phone": "+918879778527",
        "location": "Mumbai",
        "division-id": "OPS",
        "division-name": "Operations",
        "position-name": "Business Process Owner, Commercial Operations",
        "email": "Piyush.Jain@maersktankers.com",
        "ice-id": "",
        "segments": ""
    },
    {
        "first-name": "Sahil",
        "last-name": "Chadha",
        "phone": "+4540115370",
        "location": "Copenhagen",
        "division-id": "PARSERV",
        "division-name": "Partner Services",
        "position-name": "Partner Manager",
        "email": "Sahil.Chadha@maersktankers.com",
        "ice-id": "",
        "segments": ""
    },
    {
        "first-name": "Jørgen-Ole",
        "last-name": "Christensen",
        "phone": "+4560394144",
        "location": "Copenhagen",
        "division-id": "FLEXIOPS",
        "division-name": "Operations",
        "position-name": "Senior Operator",
        "email": "jorgenole.christensen@maersktankers.com",
        "ice-id": "",
        "segments": "Flexi"
    },
    {
        "first-name": "Jacob",
        "last-name": "Pedersen",
        "phone": "+4521763626",
        "location": "Copenhagen",
        "division-id": "MR",
        "division-name": "Chartering",
        "position-name": "Senior Charterer",
        "email": "jacob.pedersen@maersktankers.com",
        "ice-id": "",
        "segments": "MR"
    },
    {
        "first-name": "Faisal",
        "last-name": "Rizan",
        "phone": "+6581212088",
        "location": "Singapore",
        "division-id": "CITYCHART",
        "division-name": "Chartering",
        "position-name": "Charterer",
        "email": "faisal.rizan@maersktankers.com",
        "ice-id": "",
        "segments": "City"
    },
    {
        "first-name": "Jessie",
        "last-name": "Heng",
        "phone": "+6596579156",
        "location": "Singapore",
        "division-id": "CITYCHART",
        "division-name": "Chartering",
        "position-name": "Senior Charterer",
        "email": "jessie.heng@maersktankers.com",
        "ice-id": "",
        "segments": "City"
    },
    {
        "first-name": "Lars",
        "last-name": "Richter",
        "phone": "+4530381150",
        "location": "Copenhagen",
        "division-id": "INTOPSCPH",
        "division-name": "Operations",
        "position-name": "Operator",
        "email": "lars.richter@maersktankers.com",
        "ice-id": "",
        "segments": "Intermediate"
    },
    {
        "first-name": "Sanjeev",
        "last-name": "Ranjan",
        "phone": "+918879688771",
        "location": "Mumbai",
        "division-id": "HANDYOPSMUM",
        "division-name": "Operations",
        "position-name": "Handy Operations Manager",
        "email": "Sanjeev.Ranjan@maersktankers.com",
        "ice-id": "",
        "segments": "Handy"
    },
    {
        "first-name": "Teik Zhen Robin",
        "last-name": "Lim",
        "phone": "+6598309587",
        "location": "Singapore",
        "division-id": "LR2CHART",
        "division-name": "Chartering",
        "position-name": "Senior Charterer",
        "email": "Robin.lim@maersktankers.com",
        "ice-id": "",
        "segments": "LR2"
    },
    {
        "first-name": "Harish",
        "last-name": "Venkatesh",
        "phone": "+6596521184",
        "location": "Singapore",
        "division-id": "LR2CHART",
        "division-name": "Chartering",
        "position-name": "Charterer",
        "email": "Harish.Venkatesh@maersktankers.com",
        "ice-id": "",
        "segments": "LR2"
    },
    {
        "first-name": "Sumeet",
        "last-name": "Sharma",
        "phone": "+917045873207",
        "location": "Mumbai",
        "division-id": "HANDYOPSMUM",
        "division-name": "Operations",
        "position-name": "Associate Voyage Manager",
        "email": "sumeet.sharma@maersktankers.com",
        "ice-id": "",
        "segments": "Handy"
    },
    {
        "first-name": "Harsh",
        "last-name": "Thakkar",
        "phone": "+6597286663",
        "location": "Singapore",
        "division-id": "LR2CHART",
        "division-name": "Chartering",
        "position-name": "Senior Charterer",
        "email": "harsh.thakkar@maersktankers.com",
        "ice-id": "",
        "segments": "LR2"
    },
    {
        "first-name": "Abhishekaa",
        "last-name": "Sunny",
        "phone": "+9170459518253",
        "location": "Mumbai",
        "division-id": "HANDYOPSMUM",
        "division-name": "Operations",
        "position-name": "Voyage Manager",
        "email": "Abhishek.Sunny@maersktankers.com",
        "ice-id": "",
        "segments": "Handy"
    },
    {
        "first-name": "Kristian",
        "last-name": "Jasper",
        "phone": "+6596729561",
        "location": "Singapore",
        "division-id": "LR2CHART",
        "division-name": "Chartering",
        "position-name": "Head of LR2",
        "email": "Kristian.Jasper@maersktankers.com",
        "ice-id": "",
        "segments": "LR2"
    },
    {
        "first-name": "Smrity",
        "last-name": "Kumari",
        "phone": "+918291927443",
        "location": "Mumbai",
        "division-id": "HANDYOPSMUM",
        "division-name": "Operations",
        "position-name": "Voyage Manager",
        "email": "smrity.sharma@maersktankers.com",
        "ice-id": "",
        "segments": "Handy"
    },
    {
        "first-name": "Christina",
        "last-name": "Legarth Jacobsen",
        "phone": "+45 22325552",
        "location": "Copenhagen",
        "division-id": "HTC",
        "division-name": "Chartering",
        "position-name": "Associate Charterer",
        "email": "christina.legarth.jacobsen@maersktankers.com",
        "ice-id": "",
        "segments": "Handy"
    },
    {
        "first-name": "Morten",
        "last-name": "Olsen",
        "phone": "+4531409974",
        "location": "Copenhagen",
        "division-id": "FREIGHTOPT",
        "division-name": "Freight Optimisation",
        "position-name": "FFA Trader",
        "email": "Morten.Olsen1@maersktankers.com",
        "ice-id": "",
        "segments": ""
    },
    {
        "first-name": "Manu",
        "last-name": "Kesavan",
        "phone": "+917045951857",
        "location": "Mumbai",
        "division-id": "HANDYOPSMUM",
        "division-name": "Operations",
        "position-name": "Senior Voyage Manager",
        "email": "Manu.Kesavan@maersktankers.com",
        "ice-id": "",
        "segments": "Handy"
    },
    {
        "first-name": "Lars",
        "last-name": "Skjødt Petersen",
        "phone": "+4561638614",
        "location": "Copenhagen",
        "division-id": "MR",
        "division-name": "Chartering",
        "position-name": "Senior Charterer",
        "email": "lars.skjodt.petersen@maersktankers.com",
        "ice-id": "",
        "segments": "MR"
    },
    {
        "first-name": "Eva",
        "last-name": "Errebo",
        "phone": "+4561552269",
        "location": "Copenhagen",
        "division-id": "FREIGHTOPT",
        "division-name": "Freight Optimisation",
        "position-name": "Head of T/C",
        "email": "Eva.Boje.Errebo@maersktankers.com",
        "ice-id": "",
        "segments": ""
    },
    {
        "first-name": "Prasun",
        "last-name": "Kumar",
        "phone": "+917045584109",
        "location": "Mumbai",
        "division-id": "HANDYOPSMUM",
        "division-name": "Operations",
        "position-name": "Voyage Manager",
        "email": "Prasun.Kumar@maersktankers.com",
        "ice-id": "",
        "segments": "Handy"
    },
    {
        "first-name": "Per",
        "last-name": "Heilmann",
        "phone": "+4529350902",
        "location": "Copenhagen",
        "division-id": "FREIGHTOPT",
        "division-name": "Freight Optimisation",
        "position-name": "Head of FFA & Trading",
        "email": "Per.Heilmann@maersktankers.com",
        "ice-id": "",
        "segments": ""
    },
    {
        "first-name": "Antriksh",
        "last-name": "Kochar",
        "phone": "+451234567",
        "location": "Mumbai",
        "division-id": "HANDYOPSMUM",
        "division-name": "Operations",
        "position-name": "Voyage Manager",
        "email": "antriksh.kochar@maersktankers.com",
        "ice-id": "",
        "segments": "Handy"
    },
    {
        "first-name": "Venil",
        "last-name": "Burboz",
        "phone": "+917798868616",
        "location": "Mumbai",
        "division-id": "HANDYOPSMUM",
        "division-name": "Operations",
        "position-name": "Voyage Manager",
        "email": "venil.burboz@maersktankers.com",
        "ice-id": "",
        "segments": "Handy"
    },
    {
        "first-name": "Tarun",
        "last-name": "Sethi",
        "phone": "+451234567",
        "location": "Mumbai",
        "division-id": "HANDYOPSMUM",
        "division-name": "Operations",
        "position-name": "Voyage Manager",
        "email": "tarun.sethi@maersktankers.com",
        "ice-id": "",
        "segments": "Handy"
    },
    {
        "first-name": "Rohan",
        "last-name": "Upadhye",
        "phone": "+918657417293",
        "location": "Mumbai",
        "division-id": "HANDYOPSMUM",
        "division-name": "Operations",
        "position-name": "Voyage Manager",
        "email": "rohan.upadhye@maersktankers.com",
        "ice-id": "",
        "segments": "Handy"
    },
    {
        "first-name": "Anders",
        "last-name": "Birk",
        "phone": "+4520264122",
        "location": "Copenhagen",
        "division-id": "MR",
        "division-name": "Chartering",
        "position-name": "Head of MR Chartering",
        "email": "Anders.Okkels.Birk@maersktankers.com",
        "ice-id": "",
        "segments": "MR"
    },
    {
        "first-name": "Garul",
        "last-name": "Kalia",
        "phone": "+91 75062 08858",
        "location": "Mumbai",
        "division-id": "HANDYOPSMUM",
        "division-name": "Operations",
        "position-name": "Voyage Manager",
        "email": "garul.kalia@maersktankers.com",
        "ice-id": "",
        "segments": "Handy"
    },
    {
        "first-name": "Nitin",
        "last-name": "Saxena",
        "phone": "+918657792003",
        "location": "Mumbai",
        "division-id": "HANDYOPSMUM",
        "division-name": "Operations",
        "position-name": "Voyage Manager",
        "email": "nitin.saxena@maersktankers.com",
        "ice-id": "",
        "segments": "Handy"
    },
    {
        "first-name": "Sandokan",
        "last-name": "Barretto",
        "phone": "+919769713671",
        "location": "Mumbai",
        "division-id": "HANDYOPSMUM",
        "division-name": "Operations",
        "position-name": "Senior Voyage Manager",
        "email": "sandokan.barretto@maersktankers.com",
        "ice-id": "",
        "segments": "Handy"
    },
    {
        "first-name": "Kis",
        "last-name": "Soegaard",
        "phone": "+4524937168",
        "location": "Copenhagen",
        "division-id": "COMM",
        "division-name": "Communications",
        "position-name": "Head of Communications",
        "email": "Kis.Soegaard@maersktankers.com",
        "ice-id": "",
        "segments": ""
    },
    {
        "first-name": "Pushkar",
        "last-name": "Mishra",
        "phone": "+918657792002",
        "location": "Mumbai",
        "division-id": "MROPSMUM",
        "division-name": "Operations",
        "position-name": "Voyage Manager",
        "email": "pushkar.mishra@maersktankers.com",
        "ice-id": "",
        "segments": "MR"
    },
    {
        "first-name": "Sumit",
        "last-name": "Sabarwal",
        "phone": "+4530693844",
        "location": "Copenhagen",
        "division-id": "CHTCPH",
        "division-name": "Chartering",
        "position-name": "Charterer",
        "email": "Sumit.Sabarwal@maersktankers.com",
        "ice-id": "",
        "segments": "Handy"
    },
    {
        "first-name": "Juliane",
        "last-name": "von Wiren",
        "phone": "+4524934794",
        "location": "Copenhagen",
        "division-id": "COMM",
        "division-name": "Communications",
        "position-name": "Communications Partner",
        "email": "Juliane.von.Wiren@maersktankers.com",
        "ice-id": "",
        "segments": ""
    },
    {
        "first-name": "Kartik",
        "last-name": "Mohan",
        "phone": "+918657792001",
        "location": "Mumbai",
        "division-id": "MROPSMUM",
        "division-name": "Operations",
        "position-name": "Voyage Manager",
        "email": "kartik.mohan@maersktankers.com",
        "ice-id": "",
        "segments": "MR"
    },
    {
        "first-name": "Mehmet",
        "last-name": "Demir",
        "phone": null,
        "location": "Copenhagen",
        "division-id": "CHTCPH",
        "division-name": "Chartering",
        "position-name": "Charterer",
        "email": "mehmet.demir@maersktankers.com",
        "ice-id": "",
        "segments": "Handy"
    },
    {
        "first-name": "Amit",
        "last-name": "Anshu",
        "phone": "+919167968176",
        "location": "Mumbai",
        "division-id": "MROPSMUM",
        "division-name": "Operations",
        "position-name": "MR/LR2 Operations Manager",
        "email": "amit.anshu@maersktankers.com",
        "ice-id": "",
        "segments": "MR"
    },
    {
        "first-name": "Alexander",
        "last-name": "Mohtram",
        "phone": "+451234567",
        "location": "Copenhagen",
        "division-id": "CHTCPH",
        "division-name": "Chartering",
        "position-name": "Charterer",
        "email": "alexander.mohtram@maersktankers.com",
        "ice-id": "",
        "segments": "Handy"
    },
    {
        "first-name": "Hilde",
        "last-name": "Johannessen",
        "phone": "+4551211090",
        "location": "Copenhagen",
        "division-id": "CHTCPH",
        "division-name": "Chartering",
        "position-name": "Charterer, Handytankers",
        "email": "Hilde.Johannessen@maersktankers.com",
        "ice-id": "",
        "segments": "Handy"
    },
    {
        "first-name": "Sandeep",
        "last-name": "Singh",
        "phone": "+917045951852",
        "location": "Mumbai",
        "division-id": "MROPSMUM",
        "division-name": "Operations",
        "position-name": "Senior Analyst Freight & Demurrage",
        "email": "Sandeep.Singh@maersktankers.com",
        "ice-id": "",
        "segments": "MR"
    },
    {
        "first-name": "Jesper",
        "last-name": "Frolich-Hansen",
        "phone": "+4551221069",
        "location": "Copenhagen",
        "division-id": "CHTCPH",
        "division-name": "Chartering",
        "position-name": "Senior Charterer & Deputy, Handytankers",
        "email": "Jesper.Frolich-Hansen@maersktankers.com",
        "ice-id": "",
        "segments": "Handy"
    },
    {
        "first-name": "Liang",
        "last-name": "Ji",
        "phone": "+6596740947",
        "location": "Singapore",
        "division-id": "MRSIN",
        "division-name": "Chartering",
        "position-name": "Charterer",
        "email": "Liang.ji1@maersktankers.com",
        "ice-id": "",
        "segments": "MR"
    },
    {
        "first-name": "Venkatesh",
        "last-name": "Dutt",
        "phone": "+6597100954",
        "location": "Singapore",
        "division-id": "CITYOPS",
        "division-name": "Operations",
        "position-name": "Segment Operations Manager",
        "email": "venkatesh.dutt@maersktankers.com",
        "ice-id": "",
        "segments": "City"
    },
    {
        "first-name": "Lalit",
        "last-name": "Chaturvedi",
        "phone": "+919930315104",
        "location": "Mumbai",
        "division-id": "MTOPSMUM",
        "division-name": "Operations",
        "position-name": "Senior Manager - Freight and Demurrage",
        "email": "Lalit.Chaturvedi@maersktankers.com",
        "ice-id": "",
        "segments": "Handy"
    },
    {
        "first-name": "Anna",
        "last-name": "Huddleston",
        "phone": "+4521996588",
        "location": "Copenhagen",
        "division-id": "CHTCPH",
        "division-name": "Chartering",
        "position-name": "Senior Charterer",
        "email": "Anna.Huddleston@maersktankers.com",
        "ice-id": "",
        "segments": "Handy"
    },
    {
        "first-name": "Jian",
        "last-name": "ZHU",
        "phone": "+6590933174",
        "location": "Singapore",
        "division-id": "MRSIN",
        "division-name": "Chartering",
        "position-name": "Charterer",
        "email": "jian.zhu@maersktankers.com",
        "ice-id": "",
        "segments": "MR"
    },
    {
        "first-name": "Karan",
        "last-name": "Mehta",
        "phone": "+4540268551",
        "location": "Copenhagen",
        "division-id": "CHTCPH",
        "division-name": "Chartering",
        "position-name": "Charterer, Handytankers",
        "email": "Karan.Mehta@maersktankers.com",
        "ice-id": "",
        "segments": "Handy"
    },
    {
        "first-name": "Harshad",
        "last-name": "Kshirsagar",
        "phone": "+919833884217",
        "location": "Mumbai",
        "division-id": "MTOPSMUM",
        "division-name": "Operations",
        "position-name": "Senior Disbursement Account Analyst",
        "email": "Harshad.Kshirsagar@maersktankers.com",
        "ice-id": "",
        "segments": "Handy"
    },
    {
        "first-name": "Bharat",
        "last-name": "Midha",
        "phone": "+6581262680",
        "location": "Singapore",
        "division-id": "CITYOPS",
        "division-name": "Operations",
        "position-name": "Commercial Operator",
        "email": "bharat.midha@maersktankers.com",
        "ice-id": "",
        "segments": "City"
    },
    {
        "first-name": "William",
        "last-name": "Mew",
        "phone": "+4520228639",
        "location": "Copenhagen",
        "division-id": "CHTCPH",
        "division-name": "Chartering",
        "position-name": "Senior Charterer, Handytankers",
        "email": "William.Mew@maersktankers.com",
        "ice-id": "",
        "segments": "Handy"
    },
    {
        "first-name": "Azharuddin",
        "last-name": "Shah",
        "phone": "+918898393371",
        "location": "Mumbai",
        "division-id": "MTOPSMUM",
        "division-name": "Operations",
        "position-name": "Senior Analyst, Freight & Demurrage",
        "email": "Azharuddin.Shah@maersktankers.com",
        "ice-id": "",
        "segments": "Handy"
    },
    {
        "first-name": "Smita",
        "last-name": "Sharma",
        "phone": "+919205428650",
        "location": "Mumbai",
        "division-id": "MROPSMUM",
        "division-name": "Operations",
        "position-name": "Operator",
        "email": "smita.sharma@maersktankers.com",
        "ice-id": "",
        "segments": "MR"
    },
    {
        "first-name": "Amit",
        "last-name": "Srivastava",
        "phone": "+919140388522",
        "location": "Mumbai",
        "division-id": "MTOPSMUM",
        "division-name": "Operations",
        "position-name": "Senior Analyst Commercial Claims",
        "email": "amit.srivastava@maersktankers.com",
        "ice-id": "",
        "segments": "Handy"
    },
    {
        "first-name": "Shashank",
        "last-name": "Yadav",
        "phone": "+919867292500",
        "location": "Mumbai",
        "division-id": "MTOPSMUM",
        "division-name": "Operations",
        "position-name": "Senior Analyst Freight & Demurrage",
        "email": "shashank.yadav@maersktankers.com",
        "ice-id": "",
        "segments": "Handy"
    },
    {
        "first-name": "Vishwajeet",
        "last-name": "Singh",
        "phone": "+917028055579",
        "location": "Mumbai",
        "division-id": "MROPSMUM",
        "division-name": "Operations",
        "position-name": "Voyage Manager",
        "email": "Vishwajeet.Singh@maersktankers.com",
        "ice-id": "",
        "segments": "MR"
    },
    {
        "first-name": "Martin",
        "last-name": "Crone Kjeldsen",
        "phone": "+12032919366",
        "location": "Houston",
        "division-id": "MRCHARTUS",
        "division-name": "Chartering",
        "position-name": "Charterer",
        "email": "martin.kjeldsen@maersktankers.com",
        "ice-id": "",
        "segments": "MR;Handy;Intermediate"
    },
    {
        "first-name": "Rishi",
        "last-name": "Razdan",
        "phone": "+919769260875",
        "location": "Mumbai",
        "division-id": "MTOPSMUM",
        "division-name": "Operations",
        "position-name": "Analyst Freight & Demurrage",
        "email": "rishi.razdan@maersktankers.com",
        "ice-id": "",
        "segments": "Handy"
    },
    {
        "first-name": "Cesar",
        "last-name": "Nino",
        "phone": "+16463274314",
        "location": "Houston",
        "division-id": "MRCHARTUS",
        "division-name": "Chartering",
        "position-name": "Charterer",
        "email": "Cesar.Nino@maersktankers.com",
        "ice-id": "",
        "segments": "MR;Handy;Intermediate"
    },
    {
        "first-name": "Pratima",
        "last-name": "Vichare",
        "phone": "+919664597498",
        "location": "Mumbai",
        "division-id": "MTOPSMUM",
        "division-name": "Operations",
        "position-name": "Analyst Freight & Demurrage",
        "email": "pratima.vichare@maersktankers.com",
        "ice-id": "",
        "segments": "Handy"
    },
    {
        "first-name": "Sagar",
        "last-name": "Shetye",
        "phone": "+919987885733",
        "location": "Mumbai",
        "division-id": "MTOPSMUM",
        "division-name": "Operations",
        "position-name": "Senior Claims Analyst",
        "email": "Sagar.Shetye@maersktankers.com",
        "ice-id": "",
        "segments": "Handy"
    },
    {
        "first-name": "Priyesh",
        "last-name": "Kumar",
        "phone": "+918745837417",
        "location": "Mumbai",
        "division-id": "MTOPSMUM",
        "division-name": "Operations",
        "position-name": "Senior Analyst ,Claims",
        "email": "Priyesh.Kumar@maersktankers.com",
        "ice-id": "",
        "segments": "Handy"
    },
    {
        "first-name": "Vivek",
        "last-name": "Singh",
        "phone": "+919829102562",
        "location": "Mumbai",
        "division-id": "MTOPSMUM",
        "division-name": "Operations",
        "position-name": "Sr Analyst",
        "email": "Vivek.Singh@maersktankers.com",
        "ice-id": "",
        "segments": "Handy"
    },
    {
        "first-name": "Akhilesh",
        "last-name": "Gupta",
        "phone": "+918879077125",
        "location": "Mumbai",
        "division-id": "MTOPSMUM",
        "division-name": "Operations",
        "position-name": "Head of Freight, Demurrage and Claims",
        "email": "Akhilesh.Gupta@maersktankers.com",
        "ice-id": "",
        "segments": "Handy"
    },
    {
        "first-name": "Jayshree",
        "last-name": "Zore",
        "phone": "+918291203738",
        "location": "Mumbai",
        "division-id": "MTOPSMUM",
        "division-name": "Operations",
        "position-name": "Analyst, Demurrage & Freight",
        "email": "jayshree.zore@maersktankers.com",
        "ice-id": "",
        "segments": "Handy"
    },
    {
        "first-name": "Ankit",
        "last-name": "Shetty",
        "phone": "+451234567",
        "location": "Mumbai",
        "division-id": "MTOPSMUM",
        "division-name": "Operations",
        "position-name": "Senior Analyst, Freight & Demurrage",
        "email": "ankit.shetty@maersktankers.com",
        "ice-id": "",
        "segments": "Handy"
    },
    {
        "first-name": "Neelabh",
        "last-name": "Srivastav",
        "phone": "+919619192353",
        "location": "Mumbai",
        "division-id": "MROPSMUM",
        "division-name": "Operations",
        "position-name": "Voyage Manager",
        "email": "neelabh.srivastav@maersktankers.com",
        "ice-id": "",
        "segments": "MR"
    },
    {
        "first-name": "Savitha",
        "last-name": "Nair",
        "phone": "+919619076850",
        "location": "Mumbai",
        "division-id": "MTOPSMUM",
        "division-name": "Operations",
        "position-name": "Manager - Freight and Demurrage",
        "email": "savitha.nair@maersktankers.com",
        "ice-id": "",
        "segments": "Handy"
    },
    {
        "first-name": "Benjamin",
        "last-name": "Cervone",
        "phone": "+13307208835",
        "location": "Houston",
        "division-id": "MRCHARTUS",
        "division-name": "Chartering",
        "position-name": "Charterer",
        "email": "Benjamin.Cervone@maersktankers.com",
        "ice-id": "",
        "segments": "MR;Handy;Intermediate"
    },
    {
        "first-name": "Vinayak",
        "last-name": "Pai",
        "phone": "+918291265690",
        "location": "Mumbai",
        "division-id": "MROPSMUM",
        "division-name": "Operations",
        "position-name": "Voyage Manager",
        "email": "vinayak.pai@maersktankers.com",
        "ice-id": "",
        "segments": "MR"
    },
    {
        "first-name": "Gokulraj",
        "last-name": "Ganeshkumar",
        "phone": "+917045951399",
        "location": "Mumbai",
        "division-id": "MROPSMUM",
        "division-name": "Operations",
        "position-name": "Voyage Manager",
        "email": "Gokulraj.Ganeshkumar@maersktankers.com",
        "ice-id": "",
        "segments": "MR"
    },
    {
        "first-name": "Gregory",
        "last-name": "Smith",
        "phone": "+12032467033",
        "location": "Houston",
        "division-id": "MRCHARTUS",
        "division-name": "Chartering",
        "position-name": "Charterer",
        "email": "greg.smith@maersktankers.com",
        "ice-id": "",
        "segments": "MR;Handy;Intermediate"
    },
    {
        "first-name": "Shantanu",
        "last-name": "Jog",
        "phone": "+918291076717",
        "location": "Mumbai",
        "division-id": "MROPSMUM",
        "division-name": "Operations",
        "position-name": "Voyage Manager",
        "email": "shantanu.jog@maersktankers.com",
        "ice-id": "",
        "segments": "MR"
    },
    {
        "first-name": "Samy",
        "last-name": "Habiba",
        "phone": "+17132317561",
        "location": "Houston",
        "division-id": "MRCHARTUS",
        "division-name": "Chartering",
        "position-name": "Charterer",
        "email": "samy.habiba@maersktankers.com",
        "ice-id": "",
        "segments": "MR;Handy;Intermediate"
    },
    {
        "first-name": "Subhash",
        "last-name": "Pithisaria",
        "phone": "+917506717352",
        "location": "Mumbai",
        "division-id": "MROPSMUM",
        "division-name": "Operations",
        "position-name": "Voyage Manager",
        "email": "subhash.pithisaria@maersktankers.com",
        "ice-id": "",
        "segments": "MR"
    },
    {
        "first-name": "Neha",
        "last-name": "Dudeja",
        "phone": "+918291265688",
        "location": "Mumbai",
        "division-id": "MROPSMUM",
        "division-name": "Operations",
        "position-name": "Voyage Manager",
        "email": "neha.dudeja@maersktankers.com",
        "ice-id": "",
        "segments": "MR"
    },
    {
        "first-name": "Jasween",
        "last-name": "Kaur",
        "phone": "+918879970835",
        "location": "Mumbai",
        "division-id": "MROPSMUM",
        "division-name": "Operations",
        "position-name": "Senior Voyage Manager",
        "email": "jasween.kaur@maersktankers.com",
        "ice-id": "",
        "segments": "MR"
    },
    {
        "first-name": "Amit",
        "last-name": "Rawat",
        "phone": "+917506648784",
        "location": "Mumbai",
        "division-id": "MROPSMUM",
        "division-name": "Operations",
        "position-name": "Senior Voyage Manager",
        "email": "amit.rawat@maersktankers.com",
        "ice-id": "",
        "segments": "MR"
    },
    {
        "first-name": "Rupa",
        "last-name": "Rao",
        "phone": "+917045951854",
        "location": "Mumbai",
        "division-id": "MTOPSMUM",
        "division-name": "Operations",
        "position-name": "Manager Freight & Demurrage",
        "email": "Rupa.Rao@maersktankers.com",
        "ice-id": "",
        "segments": "Handy"
    },
    {
        "first-name": "Sushil",
        "last-name": "Bhushan",
        "phone": "+917506934134",
        "location": "Mumbai",
        "division-id": "MROPSMUM",
        "division-name": "Operations",
        "position-name": "Senior Voyage Manager",
        "email": "sushil.bhushan@maersktankers.com",
        "ice-id": "",
        "segments": "MR"
    },
    {
        "first-name": "Jesso",
        "last-name": "Joy",
        "phone": "+919833783424",
        "location": "Mumbai",
        "division-id": "MROPSMUM",
        "division-name": "Operations",
        "position-name": "Senior Voyage Manager",
        "email": "jesso.joy@maersktankers.com",
        "ice-id": "",
        "segments": "MR"
    }
]
}
